read/__init__.py
read-0.0.1.dist-info/METADATA
read-0.0.1.dist-info/WHEEL
read-0.0.1.dist-info/top_level.txt
read-0.0.1.dist-info/RECORD
