Metadata-Version: 2.1
Name: read
Version: 0.0.1
Summary: Read files faster
Home-page: https://gitee.com/yanhuihang/read
Author: YAN Hui Hang, GDUFS
Author-email: yanhuihang@126.com
License: UNKNOWN
Platform: UNKNOWN
Classifier: Programming Language :: Python :: 3
Classifier: Operating System :: OS Independent
Requires-Python: >=3.6
